{"version":"2.1","video":{"currentEpisode":80072030,"type":"show","id":80071911,"merchedVideoId":null,"title":"Fixer Upper","synopsis":"Join Texas design experts Chip and Joanna Gaines as they help homebuyers turn less-than-perfect properties into dream houses.","rating":"TV-G","cinematch":{"value":5.0,"type":"predicted"},"requiresPin":false,"requiresAdultVerification":false,"artwork":[{"w":1280,"h":720,"url":"http://cdn1.nflximg.net/ipl/95320/aa1b767afa7b33f36074aaf8cf7a7a2338ad3c5c.jpg"},{"w":1280,"h":720,"url":"http://cdn1.nflximg.net/ipl/95320/aa1b767afa7b33f36074aaf8cf7a7a2338ad3c5c.jpg"}],"boxart":[{"w":426,"h":607,"url":"http://cdn1.nflximg.net/ipl/93300/8a026f02de7e622ddd2229d157930db8313cac2d.jpg"},{"w":284,"h":405,"url":"http://cdn1.nflximg.net/ipl/93297/9c767dcb4495f540ec72e34a038ba52de05e63e1.jpg"}],"seasons":[{"id":80072216,"title":"Season 1","year":2014,"seq":1,"shortName":"S1","longName":"Season 1","episodes":[{"id":80072030,"episodeId":80072030,"synopsis":"Chip and Joanna help a couple pick a fixer-upper in Castle Heights, an upscale Waco neighborhood that's full of mansions.","title":"Looking Old but Feeling New","seq":1,"runtime":2594,"creditsOffset":2594,"autoplayable":true,"start":1459494000000,"end":1475305200000,"hd":true,"requiresPin":false,"requiresAdultVerification":false,"progressImageRoot":"http://tp.akam.nflximg.com/tpa4/667/2123673667/","stills":[{"w":1920,"h":1080,"url":"http://so0.akam.nflximg.com/soa1/360/819857360.jpg"}],"bookmark":{"offset":-1,"watchedDate":0}},{"id":80072031,"episodeId":80072031,"synopsis":"Chip and Joanna take Chuck and Charmaine on a tour of Waco's historic Sanger Heights neighborhood, which is undergoing a revitalization.","title":"Young Family Takes on History","seq":2,"runtime":2596,"creditsOffset":2595,"autoplayable":true,"start":1459494000000,"end":1475305200000,"hd":true,"requiresPin":false,"requiresAdultVerification":false,"progressImageRoot":"http://tp.akam.nflximg.com/tpa1/303/137355303/","stills":[{"w":1920,"h":1080,"url":"http://so1.akam.nflximg.com/soa5/903/846984903.jpg"}],"bookmark":{"offset":-1,"watchedDate":0}},{"id":80072032,"episodeId":80072032,"synopsis":"Heath and Becky Ivy tour Woodway, Texas, in search of a home to accommodate his growing business and their growing family.","title":"Nomad Family Seeks Final Home","seq":3,"runtime":2595,"creditsOffset":2595,"autoplayable":true,"start":1459494000000,"end":1475305200000,"hd":true,"requiresPin":false,"requiresAdultVerification":false,"progressImageRoot":"http://tp.akam.nflximg.com/tpa1/507/144850507/","stills":[{"w":1920,"h":1080,"url":"http://so0.akam.nflximg.com/soa4/563/819753563.jpg"}],"bookmark":{"offset":-1,"watchedDate":0}},{"id":80072033,"episodeId":80072033,"synopsis":"After a tough divorce, single mom Karla turns to Chip and Joanna for help in finding the right home to start life's next chapter.","title":"New Home New Life for Mom","seq":4,"runtime":2595,"creditsOffset":2594,"autoplayable":true,"start":1459494000000,"end":1475305200000,"hd":true,"requiresPin":false,"requiresAdultVerification":false,"progressImageRoot":"http://tp.akam.nflximg.com/tpa5/560/61623560/","stills":[{"w":1920,"h":1080,"url":"http://so1.akam.nflximg.com/soa7/621/1540566621.jpg"}],"bookmark":{"offset":-1,"watchedDate":0}},{"id":80072034,"episodeId":80072034,"synopsis":"Chip and Joanna help Carolyn Muska, who lost her home and her husband in a tragic fertilizer plant explosion, start the next chapter of her life.","title":"Client Rebuilds After Tragedy","seq":5,"runtime":2596,"creditsOffset":2595,"autoplayable":true,"start":1459494000000,"end":1475305200000,"hd":true,"requiresPin":false,"requiresAdultVerification":false,"progressImageRoot":"http://tp.akam.nflximg.com/tpa2/665/148793665/","stills":[{"w":1920,"h":1080,"url":"http://so0.akam.nflximg.com/soa2/838/913196838.jpg"}],"bookmark":{"offset":-1,"watchedDate":0}},{"id":80072035,"episodeId":80072035,"synopsis":"A Waco couple expecting their first child seeks Chip and Joanna's help in finding a home with plenty of bedrooms inside and plenty of acreage outside.","title":"Academics Seek Acreage","seq":6,"runtime":2593,"creditsOffset":2592,"autoplayable":true,"start":1459494000000,"end":1475305200000,"hd":true,"requiresPin":false,"requiresAdultVerification":false,"progressImageRoot":"http://tp.akam.nflximg.com/tpa5/217/63202217/","stills":[{"w":1920,"h":1080,"url":"http://so1.akam.nflximg.com/soa5/096/800156096.jpg"}],"bookmark":{"offset":-1,"watchedDate":0}},{"id":80072036,"episodeId":80072036,"synopsis":"Three grown siblings seek a home for their parents, missionaries who spend nearly all their time overseas and need a stateside retreat.","title":"Missionaries Retreat in Waco","seq":7,"runtime":2596,"creditsOffset":2595,"autoplayable":true,"start":1459494000000,"end":1475305200000,"hd":true,"requiresPin":false,"requiresAdultVerification":false,"progressImageRoot":"http://tp.akam.nflximg.com/tpa5/736/148835736/","stills":[{"w":1920,"h":1080,"url":"http://so0.akam.nflximg.com/soa1/855/914465855.jpg"}],"bookmark":{"offset":-1,"watchedDate":0}},{"id":80072037,"episodeId":80072037,"synopsis":"A doctor and his active, outdoorsy family recruit Chip and Joanna to help them find a European-inspired home near Lake Waco.","title":"French Country Sought in Waco","seq":8,"runtime":2594,"creditsOffset":2594,"autoplayable":true,"start":1459494000000,"end":1475305200000,"hd":true,"requiresPin":false,"requiresAdultVerification":false,"progressImageRoot":"http://tp.akam.nflximg.com/tpa2/558/62986558/","stills":[{"w":1920,"h":1080,"url":"http://so1.akam.nflximg.com/soa7/087/820631087.jpg"}],"bookmark":{"offset":-1,"watchedDate":0}},{"id":80072038,"episodeId":80072038,"synopsis":"Married doctors with three kids of their own are on the lookout for a farmhouse big enough to fill with plenty of foster children.","title":"Physicians Seek Farmhouse","seq":9,"runtime":2596,"creditsOffset":2595,"autoplayable":true,"start":1459494000000,"end":1475305200000,"hd":true,"requiresPin":false,"requiresAdultVerification":false,"progressImageRoot":"http://tp.akam.nflximg.com/tpa2/190/149910190/","stills":[{"w":1920,"h":1080,"url":"http://so0.akam.nflximg.com/soa1/797/820281797.jpg"}],"bookmark":{"offset":-1,"watchedDate":0}},{"id":80072039,"episodeId":80072039,"synopsis":"Returning to Texas from Oklahoma, Chip and Joanna help a couple find a house with Lone Star style that doesn't go overboard.","title":"Texan Family Returns to Roots","seq":10,"runtime":2594,"creditsOffset":2593,"autoplayable":true,"start":1459494000000,"end":1475305200000,"hd":true,"requiresPin":false,"requiresAdultVerification":false,"progressImageRoot":"http://tp.akam.nflximg.com/tpa5/782/62971782/","stills":[{"w":1920,"h":1080,"url":"http://so1.akam.nflximg.com/soa2/179/819275179.jpg"}],"bookmark":{"offset":-1,"watchedDate":0}},{"id":80072040,"episodeId":80072040,"synopsis":"Chip and Joanna show big-city dwellers Clint and Kelly Harp the Brook Oaks neighborhood in hopes of finding an urban-style home.","title":"Craftsmen Crave Urban Feel","seq":11,"runtime":2595,"creditsOffset":2595,"autoplayable":true,"start":1459494000000,"end":1475305200000,"hd":true,"requiresPin":false,"requiresAdultVerification":false,"progressImageRoot":"http://tp.akam.nflximg.com/tpa1/410/61392410/","stills":[{"w":1920,"h":1080,"url":"http://so0.akam.nflximg.com/soa1/086/846727086.jpg"}],"bookmark":{"offset":-1,"watchedDate":0}},{"id":80072041,"episodeId":80072041,"synopsis":"A young couple is determined to move into a neighborhood where houses seldom go up for sale. Can Chip and Joanna conjure up a miracle?","title":"Couple Reach for Unreachable","seq":12,"runtime":2595,"creditsOffset":2594,"autoplayable":true,"start":1459494000000,"end":1475305200000,"hd":true,"requiresPin":false,"requiresAdultVerification":false,"progressImageRoot":"http://tp.akam.nflximg.com/tpa5/087/148401087/","stills":[{"w":1920,"h":1080,"url":"http://so1.akam.nflximg.com/soa5/031/1540966031.jpg"}],"bookmark":{"offset":-1,"watchedDate":0}},{"id":80072042,"episodeId":80072042,"synopsis":"A pair of baby boomer newlyweds look to Chip and Joanna for help finding the right home to accommodate their active lifestyles.","title":"Baby Boomers Buy Fixer Upper","seq":13,"runtime":2596,"creditsOffset":2595,"autoplayable":true,"start":1459494000000,"end":1475305200000,"hd":true,"requiresPin":false,"requiresAdultVerification":false,"progressImageRoot":"http://tp.akam.nflximg.com/tpa5/249/63409249/","stills":[{"w":1920,"h":1080,"url":"http://so0.akam.nflximg.com/soa5/329/1541293329.jpg"}],"bookmark":{"offset":-1,"watchedDate":0}}]},{"id":80098350,"title":"Season 2","year":2015,"seq":2,"shortName":"S2","longName":"Season 2","episodes":[{"id":80098222,"episodeId":80098222,"synopsis":"Chip and Joanna try to give their young clients everything they're looking for, including a fixer-upper that's close to their coffee business.","title":"Newlyweds Seek First Home","seq":1,"runtime":2579,"creditsOffset":2578,"autoplayable":true,"start":1459494000000,"end":1475305200000,"hd":true,"requiresPin":false,"requiresAdultVerification":false,"progressImageRoot":"http://tp.akam.nflximg.com/tpa2/104/78a695750ed93076aaf31e0e281f7daf/","stills":[{"w":1920,"h":1080,"url":"http://so0.akam.nflximg.com/soa1/989/256464989.jpg"}],"bookmark":{"offset":-1,"watchedDate":0}},{"id":80098223,"episodeId":80098223,"synopsis":"First-time homebuyers fall for a fixer-upper in an established neighborhood that's known for big lots. But the renovation also brings big problems.","title":"Young Couple Chooses Old Home","seq":2,"runtime":2580,"creditsOffset":2576,"autoplayable":true,"start":1459494000000,"end":1475305200000,"hd":true,"requiresPin":false,"requiresAdultVerification":false,"progressImageRoot":"http://tp.akam.nflximg.com/tpa5/136/990a732ed533716889b924e7f8346a4c/","stills":[{"w":1920,"h":1080,"url":"http://so1.akam.nflximg.com/soa3/085/312000085.jpg"}],"bookmark":{"offset":-1,"watchedDate":0}},{"id":80098224,"episodeId":80098224,"synopsis":"A homebuilder and a real estate agent are reluctant to look at fixer-uppers until Joanna and Chip convince them there's serious potential.","title":"Homebuilders Seek Fixer Upper","seq":3,"runtime":2579,"creditsOffset":2550,"autoplayable":true,"start":1459494000000,"end":1475305200000,"hd":true,"requiresPin":false,"requiresAdultVerification":false,"progressImageRoot":"http://tp.akam.nflximg.com/tpa1/801/576e598841ceb9651ed15f6f2b9d45a7/","stills":[{"w":1920,"h":1080,"url":"http://so0.akam.nflximg.com/soa1/109/256106109.jpg"}],"bookmark":{"offset":-1,"watchedDate":0}},{"id":80098225,"episodeId":80098225,"synopsis":"A couple with a nearly empty nest wants a roomy fixer-upper on the water with plenty of extra space for visiting family.","title":"Extra Space for Blended Family","seq":4,"runtime":2580,"creditsOffset":2578,"autoplayable":true,"start":1459494000000,"end":1475305200000,"hd":true,"requiresPin":false,"requiresAdultVerification":false,"progressImageRoot":"http://tp.akam.nflximg.com/tpa2/342/cbd6cb87aa6c9c733db2de26f7bb9715/","stills":[{"w":1920,"h":1080,"url":"http://so1.akam.nflximg.com/soa6/322/311582322.jpg"}],"bookmark":{"offset":-1,"watchedDate":0}},{"id":80098226,"episodeId":80098226,"synopsis":"A new baby's imminent arrival puts pressure on Chip and Joanna to find the perfect fixer-upper for their expectant clients.","title":"Expectant Couple Seeks Nest","seq":5,"runtime":2579,"creditsOffset":2577,"autoplayable":true,"start":1459494000000,"end":1475305200000,"hd":true,"requiresPin":false,"requiresAdultVerification":false,"progressImageRoot":"http://tp.akam.nflximg.com/tpa1/583/58dac8292d9d5949723abb40517f7a29/","stills":[{"w":1920,"h":1080,"url":"http://so0.akam.nflximg.com/soa3/963/255483963.jpg"}],"bookmark":{"offset":-1,"watchedDate":0}},{"id":80098227,"episodeId":80098227,"synopsis":"When an old high school friend moves back to Texas, Joanna and Chip step in to help his family find the perfect fixer-upper.","title":"High School Friend Seeks Fixer","seq":6,"runtime":2581,"creditsOffset":2580,"autoplayable":true,"start":1459494000000,"end":1475305200000,"hd":true,"requiresPin":false,"requiresAdultVerification":false,"progressImageRoot":"http://tp.akam.nflximg.com/tpa1/383/c6a3bb0ca9274fc7d263e260601bd1fe/","stills":[{"w":1920,"h":1080,"url":"http://so1.akam.nflximg.com/soa5/061/256828061.jpg"}],"bookmark":{"offset":-1,"watchedDate":0}},{"id":80098228,"episodeId":80098228,"synopsis":"Though their nest is nearly empty, these clients need a fixer-upper that's big enough to hold an entire football team. Can Chip and Joanna deliver?","title":"Sports Chaplain Tackles Fixer","seq":7,"runtime":2579,"creditsOffset":2578,"autoplayable":true,"start":1459494000000,"end":1475305200000,"hd":true,"requiresPin":false,"requiresAdultVerification":false,"progressImageRoot":"http://tp.akam.nflximg.com/tpa5/785/2135238b6c3bbf7393b655b86c20d7ac/","stills":[{"w":1920,"h":1080,"url":"http://so0.akam.nflximg.com/soa3/444/269347444.jpg"}],"bookmark":{"offset":-1,"watchedDate":0}},{"id":80098229,"episodeId":80098229,"synopsis":"A young couple making the transition from renting to buying fear the hidden costs of renovating a historic fixer-upper.","title":"New Homebuyers Prefer Fixer","seq":8,"runtime":2581,"creditsOffset":2579,"autoplayable":true,"start":1459494000000,"end":1475305200000,"hd":true,"requiresPin":false,"requiresAdultVerification":false,"progressImageRoot":"http://tp.akam.nflximg.com/tpa4/792/473da436e11a76447fa0505ff8ef5ac2/","stills":[{"w":1920,"h":1080,"url":"http://so1.akam.nflximg.com/soa6/577/254171577.jpg"}],"bookmark":{"offset":-1,"watchedDate":0}},{"id":80098230,"episodeId":80098230,"synopsis":"A large family with a new baby on the way wants a funky fixer-upper in an established neighborhood. But the options give them a lot to think about.","title":"Couple Seeks a Unique Fixer","seq":9,"runtime":2581,"creditsOffset":2579,"autoplayable":true,"start":1459494000000,"end":1475305200000,"hd":true,"requiresPin":false,"requiresAdultVerification":false,"progressImageRoot":"http://tp.akam.nflximg.com/tpa5/902/756e804b8c2dfe55b562fc4f2c61a4b6/","stills":[{"w":1920,"h":1080,"url":"http://so0.akam.nflximg.com/soa6/045/269845045.jpg"}],"bookmark":{"offset":-1,"watchedDate":0}},{"id":80098231,"episodeId":80098231,"synopsis":"Putting three generations under one roof is a new challenge for Chip and Joanna, but it's nothing they can't handle.","title":"Three Generations, One Fixer","seq":10,"runtime":2582,"creditsOffset":2580,"autoplayable":true,"start":1459494000000,"end":1475305200000,"hd":true,"requiresPin":false,"requiresAdultVerification":false,"progressImageRoot":"http://tp.akam.nflximg.com/tpa3/939/a00adc607f888f03b16dd2e0666f31c5/","stills":[{"w":1920,"h":1080,"url":"http://so1.akam.nflximg.com/soa1/852/277479852.jpg"}],"bookmark":{"offset":-1,"watchedDate":0}},{"id":80098232,"episodeId":80098232,"synopsis":"Chip and Joanna scope out some small-town options for a large family from the country who've outgrown their current floor plan.","title":"Country Couple Seeks Fixer","seq":11,"runtime":2579,"creditsOffset":2575,"autoplayable":true,"start":1459494000000,"end":1475305200000,"hd":true,"requiresPin":false,"requiresAdultVerification":false,"progressImageRoot":"http://tp.akam.nflximg.com/tpa3/393/28fb9375a0916ef55a3b2bd69539e9c1/","stills":[{"w":1920,"h":1080,"url":"http://so0.akam.nflximg.com/soa6/219/269767219.jpg"}],"bookmark":{"offset":-1,"watchedDate":0}},{"id":80098233,"episodeId":80098233,"synopsis":"A couple who've lived on a tiny island for years want to stay near the water when they move to Texas. But can Chip and Joanna make it happen?","title":"Island Family Seeks Space","seq":12,"runtime":2580,"creditsOffset":2579,"autoplayable":true,"start":1459494000000,"end":1475305200000,"hd":true,"requiresPin":false,"requiresAdultVerification":false,"progressImageRoot":"http://tp.akam.nflximg.com/tpa3/396/b9924a8142668b304b05c9f21c112069/","stills":[{"w":1920,"h":1080,"url":"http://so1.akam.nflximg.com/soa3/617/269543617.jpg"}],"bookmark":{"offset":-1,"watchedDate":0}},{"id":80098234,"episodeId":80098234,"synopsis":"A family with a generous budget and a taste for French country decor shops for a spacious home with hidden potential in Waco, Texas.","title":"Family Fancies French Flair","seq":13,"runtime":2581,"creditsOffset":2580,"autoplayable":true,"start":1459494000000,"end":1475305200000,"hd":true,"requiresPin":false,"requiresAdultVerification":false,"progressImageRoot":"http://tp.akam.nflximg.com/tpa4/674/f582592dbc0f8b721733dd7fb52adc85/","stills":[{"w":1920,"h":1080,"url":"http://so0.akam.nflximg.com/soa6/104/277710104.jpg"}],"bookmark":{"offset":-1,"watchedDate":0}}]}]},"trackIds":{"nextEpisode":200257858,"episodeSelector":200257859},"contentExpiry":{"willExpire":false}}
