{"version":"2.1","video":{"currentEpisode":80098379,"type":"show","id":80098319,"merchedVideoId":null,"title":"Texas Flip and Move","synopsis":"Three teams of entrepreneurs compete to be the best house flippers in Texas, buying, moving, renovating and selling homes in record-breaking time.","rating":"TV-G","cinematch":{"value":2.5,"type":"predicted"},"requiresPin":false,"requiresAdultVerification":false,"artwork":[{"w":1280,"h":720,"url":"http://cdn9.nflximg.net/ipl/28560/6d0e974b390cda190e9282b0cc9eaee7ce0915ea.jpg"},{"w":1280,"h":720,"url":"http://cdn9.nflximg.net/ipl/28560/6d0e974b390cda190e9282b0cc9eaee7ce0915ea.jpg"}],"boxart":[{"w":426,"h":607,"url":"http://cdn9.nflximg.net/ipl/27522/0b1bcfca9a0cac7a5f8a958e4e535700da756263.jpg"},{"w":284,"h":405,"url":"http://cdn9.nflximg.net/ipl/27519/b434198630ad545f4b96d3111386c581a7d812fd.jpg"}],"seasons":[{"id":80098406,"title":"Season 1","year":2015,"seq":1,"shortName":"S1","longName":"Season 1","episodes":[{"id":80098379,"episodeId":80098379,"synopsis":"Three teams of Texas real estate developers bid on houses with an eye toward flipping them, but each home must be relocated before work can begin.","title":"Old Houses Get New Addresses","seq":1,"runtime":2416,"creditsOffset":2415,"autoplayable":true,"start":1459494000000,"end":1475305200000,"hd":true,"requiresPin":false,"requiresAdultVerification":false,"progressImageRoot":"http://tp.akam.nflximg.com/tpa1/361/510cd4c90e1ad0f9feba9868d51773a7/","stills":[{"w":1920,"h":1080,"url":"http://so1.akam.nflximg.com/soa2/713/256346713.jpg"}],"bookmark":{"offset":-1,"watchedDate":0}},{"id":80098380,"episodeId":80098380,"synopsis":"Wooded property makes the Snow sisters' future woman cave a tough move, and Cody devises a solution for a house with a strange floor plan.","title":"Woman Cave vs. Home Office","seq":2,"runtime":2415,"creditsOffset":2414,"autoplayable":true,"start":1459494000000,"end":1475305200000,"hd":true,"requiresPin":false,"requiresAdultVerification":false,"progressImageRoot":"http://tp.akam.nflximg.com/tpa1/095/c6a33fc7ddb084891b9e8bbf60a09382/","stills":[{"w":1920,"h":1080,"url":"http://so0.akam.nflximg.com/soa3/222/254747222.jpg"}],"bookmark":{"offset":-1,"watchedDate":0}},{"id":80098381,"episodeId":80098381,"synopsis":"The Slays disagree on what to do with a cabin they've won, and Randy butts heads with designer Travis Lewis over renovation costs.","title":"Glam Cabin vs. Rooster Reno","seq":3,"runtime":2416,"creditsOffset":2415,"autoplayable":true,"start":1459494000000,"end":1475305200000,"hd":true,"requiresPin":false,"requiresAdultVerification":false,"progressImageRoot":"http://tp.akam.nflximg.com/tpa1/674/61121af808858b0a74fcade358390130/","stills":[{"w":1920,"h":1080,"url":"http://so1.akam.nflximg.com/soa2/527/256546527.jpg"}],"bookmark":{"offset":-1,"watchedDate":0}},{"id":80098382,"episodeId":80098382,"synopsis":"The Snow sisters revamp a house that was once a telephone operator HQ, and bidding gets out of hand on a ranch-style home that everyone wants.","title":"Historic Telephone House Flip","seq":4,"runtime":2415,"creditsOffset":2414,"autoplayable":true,"start":1459494000000,"end":1475305200000,"hd":true,"requiresPin":false,"requiresAdultVerification":false,"progressImageRoot":"http://tp.akam.nflximg.com/tpa1/194/ff1b77f36d042e522d7a3d5cf9cb1df3/","stills":[{"w":1920,"h":1080,"url":"http://so0.akam.nflximg.com/soa6/153/257162153.jpg"}],"bookmark":{"offset":-1,"watchedDate":0}},{"id":80098383,"episodeId":80098383,"synopsis":"The Snows bet Randy that they'll make more for their shipping container-turned-house than he will with his old schoolhouse-turned-studio loft.","title":"The Bet: Container vs. Loft","seq":5,"runtime":2415,"creditsOffset":2414,"autoplayable":true,"start":1459494000000,"end":1475305200000,"hd":true,"requiresPin":false,"requiresAdultVerification":false,"progressImageRoot":"http://tp.akam.nflximg.com/tpa1/987/42aeb571e02407f27432b12ed0f54d9b/","stills":[{"w":1920,"h":1080,"url":"http://so1.akam.nflximg.com/soa5/561/269397561.jpg"}],"bookmark":{"offset":-1,"watchedDate":0}},{"id":80098384,"episodeId":80098384,"synopsis":"Cody wins a house for $500 and discovers that he might have overpaid, while Randy wins a home with a great exterior but bizarre features inside.","title":"Hardwood House vs. Disaster","seq":6,"runtime":2416,"creditsOffset":2415,"autoplayable":true,"start":1459494000000,"end":1475305200000,"hd":true,"requiresPin":false,"requiresAdultVerification":false,"progressImageRoot":"http://tp.akam.nflximg.com/tpa5/038/8b17778c6f8892e1a562f4cb824d8e54/","stills":[{"w":1920,"h":1080,"url":"http://so0.akam.nflximg.com/soa7/803/277886803.jpg"}],"bookmark":{"offset":-1,"watchedDate":0}},{"id":80098385,"episodeId":80098385,"synopsis":"The Snow sisters are split on whether a cottage they won is worth the price, while Randy chooses to leave a tiny home addition on wheels as a novelty.","title":"Quaint Cottage vs. Tiny House","seq":7,"runtime":2416,"creditsOffset":2415,"autoplayable":true,"start":1459494000000,"end":1475305200000,"hd":true,"requiresPin":false,"requiresAdultVerification":false,"progressImageRoot":"http://tp.akam.nflximg.com/tpa5/627/be65b4e1db43ad3bff741d2dd383e16f/","stills":[{"w":1920,"h":1080,"url":"http://so1.akam.nflximg.com/soa3/354/298807354.jpg"}],"bookmark":{"offset":-1,"watchedDate":0}},{"id":80098386,"episodeId":80098386,"synopsis":"The Slays craft a large unused space into a walk-in closet fit for a celebrity, and the Snow sisters' gamble on a long-vacant house pays off.","title":"Custom Bling Closet Remodel","seq":8,"runtime":2416,"creditsOffset":2415,"autoplayable":true,"start":1459494000000,"end":1475305200000,"hd":true,"requiresPin":false,"requiresAdultVerification":false,"progressImageRoot":"http://tp.akam.nflximg.com/tpa5/156/48f73bb2438e652a7798b724ad2e018a/","stills":[{"w":1920,"h":1080,"url":"http://so0.akam.nflximg.com/soa5/377/277974377.jpg"}],"bookmark":{"offset":-1,"watchedDate":0}},{"id":80098387,"episodeId":80098387,"synopsis":"The Snow sisters are pleased to find that a long-vacant house is in good condition, and the Slays turn a metal school building into a residence.","title":"School Building vs. Quick Flip","seq":9,"runtime":2415,"creditsOffset":2414,"autoplayable":true,"start":1459494000000,"end":1475305200000,"hd":true,"requiresPin":false,"requiresAdultVerification":false,"progressImageRoot":"http://tp.akam.nflximg.com/tpa4/176/36571e1a6386d044518c6f065acfe8ee/","stills":[{"w":1920,"h":1080,"url":"http://so1.akam.nflximg.com/soa2/234/278058234.jpg"}],"bookmark":{"offset":-1,"watchedDate":0}}]}]},"trackIds":{"nextEpisode":200257858,"episodeSelector":200257859},"contentExpiry":{"willExpire":false}}
