{"version":"2.1","video":{"currentEpisode":80098407,"type":"show","id":80098320,"merchedVideoId":null,"title":"The Great Food Truck Race","synopsis":"Food truck teams compete as they cruise across the country, trying to outsell one another in each city to avoid elimination and land a big cash prize.","rating":"TV-G","cinematch":{"value":3.4,"type":"predicted"},"requiresPin":false,"requiresAdultVerification":false,"artwork":[{"w":1280,"h":720,"url":"http://cdn0.nflximg.net/ipl/61134/501c13ad8d979cbb93e0763ee1bb766fd94e3cc6.jpg"},{"w":1280,"h":720,"url":"http://cdn0.nflximg.net/ipl/61134/501c13ad8d979cbb93e0763ee1bb766fd94e3cc6.jpg"}],"boxart":[{"w":426,"h":607,"url":"http://cdn0.nflximg.net/ipl/54277/3f7e99690adcf3649b0acd6cf330a09f462c34b4.jpg"},{"w":284,"h":405,"url":"http://cdn0.nflximg.net/ipl/54237/f83c2b96c9b48360d7f0b0551c3e75ba1a111c81.jpg"}],"seasons":[{"id":80098255,"title":"Season 1","year":2010,"seq":1,"shortName":"S1","longName":"Season 1","episodes":[{"id":80098407,"episodeId":80098407,"synopsis":"Seven top food trucks race cross-country for a $50,000 grand prize. The contest begins with a twist when the starting line moves 100 miles south.","title":"Let's Get Rolling!","seq":1,"runtime":2532,"creditsOffset":2508,"autoplayable":true,"start":1459494000000,"end":1475305200000,"hd":false,"requiresPin":false,"requiresAdultVerification":false,"progressImageRoot":"http://tp.akam.nflximg.com/tpa2/223/bd63940415ad8b710d3493cd6d2a5c0d/","stills":[{"w":912,"h":684,"url":"http://so1.akam.nflximg.com/soa6/919/418673919.jpg"}],"bookmark":{"offset":-1,"watchedDate":0}},{"id":80098408,"episodeId":80098408,"synopsis":"On the outskirts of Santa Fe, the remaining six competitors get a new element of their challenge: They must create a new dish using local chilies.","title":"Chile Santa Fe","seq":2,"runtime":2532,"creditsOffset":2529,"autoplayable":true,"start":1459494000000,"end":1475305200000,"hd":false,"requiresPin":false,"requiresAdultVerification":false,"progressImageRoot":"http://tp.akam.nflximg.com/tpa5/458/cacb7eba51f42d5a2d7005e53a08c8e5/","stills":[{"w":912,"h":608,"url":"http://so0.akam.nflximg.com/soa7/519/1184311519.jpg"}],"bookmark":{"offset":-1,"watchedDate":0}},{"id":80098409,"episodeId":80098409,"synopsis":"In Fort Worth, contestants must butcher a side of beef and employ it in a unique dish, unaware of the event's secret judge or the huge payout.","title":"Truckin' to Texas","seq":3,"runtime":2532,"creditsOffset":2529,"autoplayable":true,"start":1459494000000,"end":1475305200000,"hd":false,"requiresPin":false,"requiresAdultVerification":false,"progressImageRoot":"http://tp.akam.nflximg.com/tpa3/104/e0ba1e0c322e53ba67ff76c9375de871/","stills":[{"w":912,"h":608,"url":"http://so1.akam.nflximg.com/soa4/830/1259597830.jpg"}],"bookmark":{"offset":-1,"watchedDate":0}},{"id":80098410,"episodeId":80098410,"synopsis":"Bad weather greets the final four in New Orleans, where they're told to close shop. Only creating the perfect catfish dish will allow them to reopen.","title":"Big Trouble in the Big Easy","seq":4,"runtime":2532,"creditsOffset":2529,"autoplayable":true,"start":1459494000000,"end":1475305200000,"hd":false,"requiresPin":false,"requiresAdultVerification":false,"progressImageRoot":"http://tp.akam.nflximg.com/tpa1/567/d8aea1ef76b5d675da9f2f3f5dc0820e/","stills":[{"w":912,"h":608,"url":"http://so0.akam.nflximg.com/soa4/743/1184603743.jpg"}],"bookmark":{"offset":-1,"watchedDate":0}},{"id":80098411,"episodeId":80098411,"synopsis":"The contestants face two unique challenges: bringing the appeal of food trucks to a small Tennessee town and making a five-course meal for cowboys.","title":"Small Town Trouble","seq":5,"runtime":2532,"creditsOffset":2531,"autoplayable":true,"start":1459494000000,"end":1475305200000,"hd":false,"requiresPin":false,"requiresAdultVerification":false,"progressImageRoot":"http://tp.akam.nflximg.com/tpa3/102/e8c8075ab99f874a2a96db5eda3565b4/","stills":[{"w":912,"h":603,"url":"http://so1.akam.nflximg.com/soa6/064/1225317064.jpg"}],"bookmark":{"offset":-1,"watchedDate":0}},{"id":80098412,"episodeId":80098412,"synopsis":"The last two contestants head for New York City, where they compete to make a sales goal in each of the five boroughs. And, as usual, there's a twist.","title":"New York Plate of Mind","seq":6,"runtime":2518,"creditsOffset":2514,"autoplayable":true,"start":1459494000000,"end":1475305200000,"hd":false,"requiresPin":false,"requiresAdultVerification":false,"progressImageRoot":"http://tp.akam.nflximg.com/tpa5/498/068de5a8dffd1fe79fac510c11013c54/","stills":[{"w":912,"h":684,"url":"http://so0.akam.nflximg.com/soa1/616/430712616.jpg"}],"bookmark":{"offset":-1,"watchedDate":0}}]},{"id":80098256,"title":"Season 2","year":2011,"seq":2,"shortName":"S2","longName":"Season 2","episodes":[{"id":80098388,"episodeId":80098388,"synopsis":"This season's race starts in Malibu, California, with a challenge incorporating one lobster and local ingredients before the teams head for Las Vegas.","title":"What Happens in Vegas","seq":1,"runtime":2533,"creditsOffset":2530,"autoplayable":true,"start":1459494000000,"end":1475305200000,"hd":true,"requiresPin":false,"requiresAdultVerification":false,"progressImageRoot":"http://tp.akam.nflximg.com/tpa2/590/071b9c1d8b65aed0d0a6f48bdf5595f3/","stills":[{"w":1916,"h":1080,"url":"http://so0.akam.nflximg.com/soa3/113/227990113.jpg"}],"bookmark":{"offset":-1,"watchedDate":0}},{"id":80098389,"episodeId":80098389,"synopsis":"On the way into Salt Lake City, the teams are challenged to create custom sausage. Tyler then shakes things up by asking the busy trucks to relocate.","title":"A Pinch of Salt Lake City","seq":2,"runtime":2533,"creditsOffset":2532,"autoplayable":true,"start":1459494000000,"end":1475305200000,"hd":true,"requiresPin":false,"requiresAdultVerification":false,"progressImageRoot":"http://tp.akam.nflximg.com/tpa1/257/f34e8a3b63c06b365369f50c81d5bc14/","stills":[{"w":1920,"h":1080,"url":"http://so1.akam.nflximg.com/soa1/086/313037086.jpg"}],"bookmark":{"offset":-1,"watchedDate":0}},{"id":80098390,"episodeId":80098390,"synopsis":"Tyler and Robin Roberts of \"Good Morning America\" announce a challenge whose winner will appear on local Denver TV, landing a big advantage.","title":"Rocky Mountain Highs and Lows","seq":3,"runtime":2533,"creditsOffset":2532,"autoplayable":true,"start":1459494000000,"end":1475305200000,"hd":true,"requiresPin":false,"requiresAdultVerification":false,"progressImageRoot":"http://tp.akam.nflximg.com/tpa2/235/caa0c70e2025c8bbbd5c5f58e7de1663/","stills":[{"w":1920,"h":1080,"url":"http://so0.akam.nflximg.com/soa6/609/229614609.jpg"}],"bookmark":{"offset":-1,"watchedDate":0}},{"id":80098391,"episodeId":80098391,"synopsis":"At Kansas State University, the teams are challenged to create an exclusive signature dish for graduation weekend ... on a student budget.","title":"Big Bites, Little Apple","seq":4,"runtime":2533,"creditsOffset":2530,"autoplayable":true,"start":1459494000000,"end":1475305200000,"hd":true,"requiresPin":false,"requiresAdultVerification":false,"progressImageRoot":"http://tp.akam.nflximg.com/tpa5/090/b41fd8dbcc66d5576c7361e281aedcb6/","stills":[{"w":1920,"h":1080,"url":"http://so1.akam.nflximg.com/soa2/635/312913635.jpg"}],"bookmark":{"offset":-1,"watchedDate":0}},{"id":80098392,"episodeId":80098392,"synopsis":"In Memphis,Tennessee, the world's barbecue capital, the final four teams have four hours to turn a 100-pound hog into a mouthwatering masterpiece.","title":"Hog Wild in Memphis","seq":5,"runtime":2533,"creditsOffset":2530,"autoplayable":true,"start":1459494000000,"end":1475305200000,"hd":true,"requiresPin":false,"requiresAdultVerification":false,"progressImageRoot":"http://tp.akam.nflximg.com/tpa2/762/87c05fc1897708c4ff187be9932a732b/","stills":[{"w":1920,"h":1080,"url":"http://so0.akam.nflximg.com/soa3/894/2099461894.jpg"}],"bookmark":{"offset":-1,"watchedDate":0}},{"id":80098393,"episodeId":80098393,"synopsis":"In Atlanta, Tyler challenges the teams to prepare a dish with Georgia trademarks peaches and peanuts, which they must wheedle from the locals.","title":"Midnight Truck to Georgia","seq":6,"runtime":2533,"creditsOffset":2532,"autoplayable":true,"start":1459494000000,"end":1475305200000,"hd":true,"requiresPin":false,"requiresAdultVerification":false,"progressImageRoot":"http://tp.akam.nflximg.com/tpa2/028/cf9fb46eedada1a14119bd88c9f72512/","stills":[{"w":1920,"h":1080,"url":"http://so1.akam.nflximg.com/soa6/145/249059145.jpg"}],"bookmark":{"offset":-1,"watchedDate":0}},{"id":80098394,"episodeId":80098394,"synopsis":"The final two race to earn $15,000 and get to the finish line in South Beach, Florida. The grand prize is at stake, but naturally, there's a twist.","title":"Miami Heat","seq":7,"runtime":2533,"creditsOffset":2528,"autoplayable":true,"start":1459494000000,"end":1475305200000,"hd":true,"requiresPin":false,"requiresAdultVerification":false,"progressImageRoot":"http://tp.akam.nflximg.com/tpa5/181/1f9fb86aa83b499b2174a87e880fd617/","stills":[{"w":1920,"h":1080,"url":"http://so0.akam.nflximg.com/soa5/354/312987354.jpg"}],"bookmark":{"offset":-1,"watchedDate":0}}]},{"id":80100042,"title":"Season 3","year":2012,"seq":3,"shortName":"S3","longName":"Season 3","episodes":[{"id":80072315,"episodeId":80072315,"synopsis":"Eight teams of aspiring food truck owners arrive in Long Beach, California, and kick off their journey in the birthplace of food trucks: Los Angeles.","title":"3,559 Miles to a Dream","seq":1,"runtime":2532,"creditsOffset":2529,"autoplayable":true,"start":1459494000000,"end":1475305200000,"hd":true,"requiresPin":false,"requiresAdultVerification":false,"progressImageRoot":"http://tp.akam.nflximg.com/tpa4/388/49906388/","stills":[{"w":1920,"h":1080,"url":"http://so1.akam.nflximg.com/soa3/536/1690718536.jpg"}],"bookmark":{"offset":-1,"watchedDate":0}},{"id":80072316,"episodeId":80072316,"synopsis":"The seven remaining teams roll into Flagstaff, Arizona, where a Truck Stop challenge requires them to create a dish featuring prickly pear cactus.","title":"Attitude at High Altitude","seq":2,"runtime":2532,"creditsOffset":2529,"autoplayable":true,"start":1459494000000,"end":1475305200000,"hd":true,"requiresPin":false,"requiresAdultVerification":false,"progressImageRoot":"http://tp.akam.nflximg.com/tpa1/066/75840066/","stills":[{"w":1920,"h":1080,"url":"http://so0.akam.nflximg.com/soa2/259/1692786259.jpg"}],"bookmark":{"offset":-1,"watchedDate":0}},{"id":80072317,"episodeId":80072317,"synopsis":"The teams visit a minor-league baseball stadium in Amarillo, Texas. Tyler challenges them to add a ballpark-inspired special to their menus.","title":"Food Trucks Are Bigger in TX","seq":3,"runtime":2532,"creditsOffset":2529,"autoplayable":true,"start":1459494000000,"end":1475305200000,"hd":true,"requiresPin":false,"requiresAdultVerification":false,"progressImageRoot":"http://tp.akam.nflximg.com/tpa4/170/48601170/","stills":[{"w":1922,"h":1080,"url":"http://so1.akam.nflximg.com/soa5/928/52755928.jpg"}],"bookmark":{"offset":-1,"watchedDate":0}},{"id":80072318,"episodeId":80072318,"synopsis":"The teams head to the bustling college town of Fayetteville, Arkansas, where they must create an amazing breakfast dish using Kellogg's Pop Tarts.","title":"Baby Got Razorback","seq":4,"runtime":2533,"creditsOffset":2529,"autoplayable":true,"start":1459494000000,"end":1475305200000,"hd":true,"requiresPin":false,"requiresAdultVerification":false,"progressImageRoot":"http://tp.akam.nflximg.com/tpa3/269/43044269/","stills":[{"w":1920,"h":1080,"url":"http://so0.akam.nflximg.com/soa7/316/1444502316.jpg"}],"bookmark":{"offset":-1,"watchedDate":0}},{"id":80072319,"episodeId":80072319,"synopsis":"In Nashville, the Truck Stop Challenge requires teams to create a down-home country-style picnic for country music stars Joey + Rory.","title":"Music City Madness","seq":5,"runtime":2532,"creditsOffset":2529,"autoplayable":true,"start":1459494000000,"end":1475305200000,"hd":true,"requiresPin":false,"requiresAdultVerification":false,"progressImageRoot":"http://tp.akam.nflximg.com/tpa2/038/44588038/","stills":[{"w":1920,"h":1080,"url":"http://so1.akam.nflximg.com/soa3/044/1455490044.jpg"}],"bookmark":{"offset":-1,"watchedDate":0}},{"id":80072320,"episodeId":80072320,"synopsis":"The final three teams roll into Cleveland, where they're challenged to create a delectable appetizer featuring a ripe Ohio tomato.","title":"Mistake by the Lake?","seq":6,"runtime":2532,"creditsOffset":2529,"autoplayable":true,"start":1459494000000,"end":1475305200000,"hd":true,"requiresPin":false,"requiresAdultVerification":false,"progressImageRoot":"http://tp.akam.nflximg.com/tpa2/908/43353908/","stills":[{"w":1920,"h":1080,"url":"http://so0.akam.nflximg.com/soa4/456/1444607456.jpg"}],"bookmark":{"offset":-1,"watchedDate":0}},{"id":80072321,"episodeId":80072321,"synopsis":"The final two teams race to Boston to begin selling. In the middle of their shift, Tyler tells them they must add a lobster dish to the menu.","title":"Where in the World Is Lubec?","seq":7,"runtime":2532,"creditsOffset":2529,"autoplayable":true,"start":1459494000000,"end":1475305200000,"hd":true,"requiresPin":false,"requiresAdultVerification":false,"progressImageRoot":"http://tp.akam.nflximg.com/tpa4/748/48355748/","stills":[{"w":1920,"h":1080,"url":"http://so1.akam.nflximg.com/soa2/080/1455720080.jpg"}],"bookmark":{"offset":-1,"watchedDate":0}}]},{"id":80099976,"title":"Season 4","year":2013,"seq":4,"shortName":"S4","longName":"Season 4","episodes":[{"id":80072322,"episodeId":80072322,"synopsis":"In Los Angeles, Tyler Florence meets the teams fighting to win the grand prize. The first challenge requires them to sell a $20 signature dish.","title":"I Left My Food Cart in San Francisco","seq":1,"runtime":2532,"creditsOffset":2529,"autoplayable":true,"start":1459494000000,"end":1475305200000,"hd":true,"requiresPin":false,"requiresAdultVerification":false,"progressImageRoot":"http://tp.akam.nflximg.com/tpa4/802/82855802/","stills":[{"w":1920,"h":1080,"url":"http://so0.akam.nflximg.com/soa2/951/1692823951.jpg"}],"bookmark":{"offset":-1,"watchedDate":0}},{"id":80072323,"episodeId":80072323,"synopsis":"The seven remaining teams head to Portland, where Tyler challenges them to go the entire first day without restocking their supplies.","title":"A Strange Brew in Portland","seq":2,"runtime":2532,"creditsOffset":2529,"autoplayable":true,"start":1459494000000,"end":1475305200000,"hd":true,"requiresPin":false,"requiresAdultVerification":false,"progressImageRoot":"http://tp.akam.nflximg.com/tpa5/462/45054462/","stills":[{"w":1920,"h":1080,"url":"http://so1.akam.nflximg.com/soa5/650/1455599650.jpg"}],"bookmark":{"offset":-1,"watchedDate":0}},{"id":80072324,"episodeId":80072324,"synopsis":"In Pocatello, Idaho, the teams purge all meat and potatoes from their menus, then dig up potatoes for new menus.","title":"Potatoes in Pocatello","seq":3,"runtime":2532,"creditsOffset":2529,"autoplayable":true,"start":1459494000000,"end":1475305200000,"hd":true,"requiresPin":false,"requiresAdultVerification":false,"progressImageRoot":"http://tp.akam.nflximg.com/tpa4/044/73377044/","stills":[{"w":1920,"h":1080,"url":"http://so0.akam.nflximg.com/soa4/227/1692734227.jpg"}],"bookmark":{"offset":-1,"watchedDate":0}},{"id":80072325,"episodeId":80072325,"synopsis":"The remaining teams meet Tyler at Mount Rushmore, then go shopping in Rapid City, South Dakota, and butcher a side of bison at a ranch.","title":"About Face in South Dakota","seq":4,"runtime":2532,"creditsOffset":2529,"autoplayable":true,"start":1459494000000,"end":1475305200000,"hd":true,"requiresPin":false,"requiresAdultVerification":false,"progressImageRoot":"http://tp.akam.nflximg.com/tpa2/673/44091673/","stills":[{"w":1920,"h":1080,"url":"http://so1.akam.nflximg.com/soa3/155/1444757155.jpg"}],"bookmark":{"offset":-1,"watchedDate":0}},{"id":80072326,"episodeId":80072326,"synopsis":"In Minneapolis, all items must be served on a stick. A second challenge in St. Paul has the teams selling dishes made with Spam.","title":"Twin Cities Double Trouble","seq":5,"runtime":2532,"creditsOffset":2529,"autoplayable":true,"start":1459494000000,"end":1475305200000,"hd":true,"requiresPin":false,"requiresAdultVerification":false,"progressImageRoot":"http://tp.akam.nflximg.com/tpa3/816/51029816/","stills":[{"w":1920,"h":1080,"url":"http://so0.akam.nflximg.com/soa1/353/1690839353.jpg"}],"bookmark":{"offset":-1,"watchedDate":0}},{"id":80072327,"episodeId":80072327,"synopsis":"The teams face a pizza challenge judged by Chicago mayor Rahm Emanuel, followed by an energetic Speed Bump and a hot dog challenge.","title":"Chicago: A Food Truck Town","seq":6,"runtime":2532,"creditsOffset":2529,"autoplayable":true,"start":1459494000000,"end":1475305200000,"hd":true,"requiresPin":false,"requiresAdultVerification":false,"progressImageRoot":"http://tp.akam.nflximg.com/tpa5/235/48284235/","stills":[{"w":1920,"h":1080,"url":"http://so1.akam.nflximg.com/soa4/651/1455885651.jpg"}],"bookmark":{"offset":-1,"watchedDate":0}},{"id":80072328,"episodeId":80072328,"synopsis":"In the Great Food Truck Race finale, the teams cover the East Coast, ending their journey at the Lincoln Memorial in Washington, D.C.","title":"Food Truck Capital Gains","seq":7,"runtime":2532,"creditsOffset":2529,"autoplayable":true,"start":1459494000000,"end":1475305200000,"hd":true,"requiresPin":false,"requiresAdultVerification":false,"progressImageRoot":"http://tp.akam.nflximg.com/tpa1/380/49315380/","stills":[{"w":1920,"h":1080,"url":"http://so0.akam.nflximg.com/soa3/377/1690389377.jpg"}],"bookmark":{"offset":-1,"watchedDate":0}}]},{"id":80099977,"title":"Season 5","year":2014,"seq":5,"shortName":"S5","longName":"Season 5","episodes":[{"id":80072329,"episodeId":80072329,"synopsis":"Tyler Florence welcomes eight new teams to Santa Barbara, California, where they must define their brands and create a signature dish.","title":"Venice Beach Brawl","seq":1,"runtime":2533,"creditsOffset":2529,"autoplayable":true,"start":1459494000000,"end":1475305200000,"hd":true,"requiresPin":false,"requiresAdultVerification":false,"progressImageRoot":"http://tp.akam.nflximg.com/tpa2/237/67193237/","stills":[{"w":1920,"h":1080,"url":"http://so1.akam.nflximg.com/soa1/211/1691305211.jpg"}],"bookmark":{"offset":-1,"watchedDate":0}},{"id":80072330,"episodeId":80072330,"synopsis":"Tyler meets the teams in Tucson, Arizona, where they must come up with a creative marketing campaign and put their twists on a local hot dog favorite.","title":"Hot Doggin' It in Tucson","seq":2,"runtime":2533,"creditsOffset":2532,"autoplayable":true,"start":1459494000000,"end":1475305200000,"hd":true,"requiresPin":false,"requiresAdultVerification":false,"progressImageRoot":"http://tp.akam.nflximg.com/tpa4/937/2133004937/","stills":[{"w":1920,"h":1080,"url":"http://so0.akam.nflximg.com/soa5/960/1337526960.jpg"}],"bookmark":{"offset":-1,"watchedDate":0}},{"id":80072331,"episodeId":80072331,"synopsis":"In Austin, Texas, the teams pair up to sell together all weekend long. Then they're sent to a Match.com event to feed hungry singles.","title":"Dinner Dates, Austin Style","seq":3,"runtime":2533,"creditsOffset":2529,"autoplayable":true,"start":1459494000000,"end":1475305200000,"hd":true,"requiresPin":false,"requiresAdultVerification":false,"progressImageRoot":"http://tp.akam.nflximg.com/tpa5/494/68257494/","stills":[{"w":1920,"h":1080,"url":"http://so1.akam.nflximg.com/soa2/231/1691849231.jpg"}],"bookmark":{"offset":-1,"watchedDate":0}},{"id":80072332,"episodeId":80072332,"synopsis":"In Oklahoma City, Tyler tests the teams' time-management skills, penalizing the team who takes the longest to get their day started.","title":"High Steaks in OKC","seq":4,"runtime":2534,"creditsOffset":2529,"autoplayable":true,"start":1459494000000,"end":1475305200000,"hd":true,"requiresPin":false,"requiresAdultVerification":false,"progressImageRoot":"http://tp.akam.nflximg.com/tpa1/910/68180910/","stills":[{"w":1920,"h":1080,"url":"http://so0.akam.nflximg.com/soa6/220/1691653220.jpg"}],"bookmark":{"offset":-1,"watchedDate":0}},{"id":80072333,"episodeId":80072333,"synopsis":"When the final four teams hit the streets of St. Louis, Tyler gives them a challenge illustrating how a premium product is as good as money in bank.","title":"Beat Me in St. Louis","seq":5,"runtime":2533,"creditsOffset":2529,"autoplayable":true,"start":1459494000000,"end":1475305200000,"hd":true,"requiresPin":false,"requiresAdultVerification":false,"progressImageRoot":"http://tp.akam.nflximg.com/tpa4/365/66809365/","stills":[{"w":1920,"h":1080,"url":"http://so1.akam.nflximg.com/soa6/301/1690870301.jpg"}],"bookmark":{"offset":-1,"watchedDate":0}},{"id":80072334,"episodeId":80072334,"synopsis":"The three remaining teams roll into Mobile, Alabama, where Tyler challenges them to cook locally. One team scores nearly 100 pounds of free shrimp.","title":"Shrimpin' Ain't Easy","seq":6,"runtime":2533,"creditsOffset":2529,"autoplayable":true,"start":1459494000000,"end":1475305200000,"hd":true,"requiresPin":false,"requiresAdultVerification":false,"progressImageRoot":"http://tp.akam.nflximg.com/tpa1/129/67887129/","stills":[{"w":1920,"h":1080,"url":"http://so0.akam.nflximg.com/soa4/151/1691422151.jpg"}],"bookmark":{"offset":-1,"watchedDate":0}},{"id":80072335,"episodeId":80072335,"synopsis":"In the grand finale, teams must revisit each of the six lessons learned throughout the race on an epic road trip from Tampa to Key West, Florida.","title":"Winning Keys in Key West","seq":7,"runtime":2533,"creditsOffset":2529,"autoplayable":true,"start":1459494000000,"end":1475305200000,"hd":true,"requiresPin":false,"requiresAdultVerification":false,"progressImageRoot":"http://tp.akam.nflximg.com/tpa2/093/68259093/","stills":[{"w":1920,"h":1080,"url":"http://so1.akam.nflximg.com/soa3/012/1692461012.jpg"}],"bookmark":{"offset":-1,"watchedDate":0}}]}]},"trackIds":{"nextEpisode":200257858,"episodeSelector":200257859},"contentExpiry":{"willExpire":false}}
